geovectorslib/__init__.py
geovectorslib/datum.py
geovectorslib/geod.py
geovectorslib/tests/__init__.py
geovectorslib/tests/conftest.py
geovectorslib/tests/test_datum.py
geovectorslib/tests/test_geod.py
geovectorslib/tests/test_utils.py
geovectorslib/utils.py
geovectorslib-1.4.dist-info/entry_points.txt
geovectorslib-1.4.dist-info/LICENSE.md
geovectorslib-1.4.dist-info/WHEEL
geovectorslib-1.4.dist-info/METADATA
geovectorslib-1.4.dist-info/RECORD
