Metadata-Version: 2.1
Name: geovectorslib
Version: 1.4
Summary: Vectorized geodesic calculations.
Home-page: https://pypi.org/project/geovectorslib
License: MIT
Author: Oleg Medvedev
Author-email: omdv.public@gmail.com
Requires-Python: >=3.7,<4.0
Classifier: Development Status :: 3 - Alpha
Classifier: License :: OSI Approved :: MIT License
Classifier: Natural Language :: English
Classifier: Operating System :: OS Independent
Classifier: Programming Language :: Python
Classifier: Programming Language :: Python :: 3
Classifier: Programming Language :: Python :: 3.10
Classifier: Programming Language :: Python :: 3.7
Classifier: Programming Language :: Python :: 3.8
Classifier: Programming Language :: Python :: 3.9
Requires-Dist: geographiclib (>=1.50,<2.0)
Requires-Dist: numpy (>=1.20.0,<2.0.0)
Project-URL: Documentation, https://geovectorslib.readthedocs.io
Project-URL: Repository, https://github.com/omdv/geovectors
